vnlb/__init__.py
vnlb/alloc.py
vnlb/impl.py
vnlb/params.py
vnlb/proc_nl.py
vnlb/proc_nn.py
vnlb/agg/__init__.py
vnlb/agg/comp_agg.py
vnlb/deno/__init__.py
vnlb/deno/bayes_est.py
vnlb/deno/bayes_est_old.py
vnlb/nvn/__init__.py
vnlb/search/__init__.py
vnlb/search/search.py
vnlb/search_mask/__init__.py
vnlb/search_mask/mask.py
vnlb/search_mask/sm_mask.py
vnlb/search_mask/trim_sims.py
vnlb/testing/__init__.py
vnlb/testing/data_loader.py
vnlb/testing/file_io.py
vnlb/testing/wrapped.py
vnlb/utils/__init__.py
vnlb/utils/batching.py
vnlb/utils/color.py
vnlb/utils/flat_areas.py
vnlb/utils/flow_utils.py
vnlb/utils/gpu_utils.py
vnlb/utils/image_utils.py
vnlb/utils/logger.py
vnlb/utils/metrics.py
vnlb/utils/patch_utils.py
vnlb/utils/sim_utils.py
vnlb/utils/sobel.py
vnlb/utils/streams.py
vnlb/utils/timer.py
vnlb/utils/utils.py
vnlb/utils/video_io.py
vnlb-0.1.1.dist-info/LICENSE
vnlb-0.1.1.dist-info/METADATA
vnlb-0.1.1.dist-info/WHEEL
vnlb-0.1.1.dist-info/top_level.txt
vnlb-0.1.1.dist-info/RECORD
