Metadata-Version: 2.1
Name: vnlb
Version: 0.1.1
Summary: A Python implementation of the Video Non-Local Bayes Denoising Method
Home-page: https://github.com/gauenk/vnlb/
Author: Kent Gauen
Author-email: kent.gauen@gmail.com
License: UNKNOWN
Project-URL: Bug Tracker, https://github.com/gauenk/vnlb/issues
Platform: UNKNOWN
Classifier: Programming Language :: Python :: 3
Classifier: License :: OSI Approved :: MIT License
Classifier: Operating System :: OS Independent
Requires-Python: >=3.6
License-File: LICENSE
Requires-Dist: numba
Requires-Dist: torch
Requires-Dist: vpss
